dotenv_derive/__init__.py
dotenv_derive/py.typed
dotenv_derive-0.1.0.dist-info/METADATA
dotenv_derive-0.1.0.dist-info/WHEEL
dotenv_derive-0.1.0.dist-info/RECORD
