Metadata-Version: 2.3
Name: dotenv-derive
Version: 0.1.0
Summary: Add your description here
Author-email: Mac Anderson <mac@macanderson.com>
Requires-Python: >=3.11
